{
  "coc.preferences.formatOnSaveFiletypes": [
    "mdx",
    "markdown",
    "markdown.mdx",
    "css",
    "html",
    "lua",
    "javascript",
    "javascriptreact",
    "json",
    "jsonc",
    "svelte",
    "typescript",
    "typescript.tsx",
    "typescriptreact"
  ],
  "eslint.probe": [
    "javascript",
    "typescript",
    "typescriptreact",
    "javascriptreact",
    "typescript.tsx",
    "svelte"
  ],
  "snippets.userSnippetsDirectory": "~/Code/dotfiles/vim/snippets",
  "snippets.extends": {
    "javascriptreact": ["javascript"],
    "typescriptreact": ["javascript"],
    "typescript": ["javascript"],
    "svelte": ["javascript", "svelte"]
  },
  "explorer.file.showHiddenFiles": true,
  "explorer.icon.enableNerdfont": true,
  "explorer.keyMappings.global": {
    "gj": false,
    "gk": false,
    "<cr>": ["expandable?", "expand", "open"],
    "v": "open:vsplit",
    "s": "open:split",
    "<esc>": "quit"
  },
  "svelte.enable-ts-plugin": true
}
